Metadata-Version: 2.1
Name: PyMPCD-MD
Version: 0.0.2
Summary: A python-based simulation package about mpcd and md.
Home-page: https://github.com/Gddr100x/PyMPCD-MD
Author: Even Wong
Author-email: evenwong@stu.cdut.edu.cn
Requires-Python: >=3.0
License-File: LICENSE
Requires-Dist: matplotlib
Requires-Dist: numpy
Requires-Dist: scipy
Requires-Dist: numba
Requires-Dist: gsd
Requires-Dist: memory-profiler
Requires-Dist: seaborn
